{
    "data": [
        {
            "id": 100011,
            "typeId": 1,
            "groupId": 1,
            "typeName": {
                "id": "4429"
            },
            "lowerLimitLevel": 60,
            "stageList": [
                24111,
                24112,
                24113,
                24114,
                24115
            ],
            "stageWeight": [
                1,
                2,
                4,
                8,
                16
            ],
            "mainId": [
                24111001,
                24112001,
                24113001,
                24114001,
                24115001
            ]
        },
        {
            "id": 100012,
            "typeId": 1,
            "groupId": 2,
            "typeName": {
                "id": "4430"
            },
            "lowerLimitLevel": 45,
            "upperLimitLevel": 59,
            "stageList": [
                24106,
                24107,
                24108,
                24109,
                24110
            ],
            "stageWeight": [
                1,
                2,
                4,
                8,
                16
            ],
            "mainId": [
                24106001,
                24107001,
                24108001,
                24109001,
                24110001
            ]
        },
        {
            "id": 100013,
            "typeId": 1,
            "groupId": 3,
            "typeName": {
                "id": "4431"
            },
            "lowerLimitLevel": 10,
            "upperLimitLevel": 44,
            "stageList": [
                24101,
                24102,
                24103,
                24104,
                24105
            ],
            "stageWeight": [
                1,
                2,
                4,
                8,
                16
            ],
            "mainId": [
                24101001,
                24102001,
                24103001,
                24104001,
                24105001
            ]
        },
        {
            "id": 100021,
            "typeId": 2,
            "groupId": 1,
            "typeName": {
                "id": "4432"
            },
            "lowerLimitLevel": 60,
            "stageList": [
                24126,
                24127,
                24128,
                24129,
                24130
            ],
            "stageWeight": [
                1,
                2,
                4,
                8,
                16
            ],
            "mainId": [
                24126001,
                24127001,
                24128001,
                24129001,
                24130001
            ]
        },
        {
            "id": 100022,
            "typeId": 2,
            "groupId": 2,
            "typeName": {
                "id": "4433"
            },
            "lowerLimitLevel": 45,
            "upperLimitLevel": 59,
            "stageList": [
                24121,
                24122,
                24123,
                24124,
                24125
            ],
            "stageWeight": [
                1,
                2,
                4,
                8,
                16
            ],
            "mainId": [
                24121001,
                24122001,
                24123001,
                24124001,
                24125001
            ]
        },
        {
            "id": 100023,
            "typeId": 2,
            "groupId": 3,
            "typeName": {
                "id": "4434"
            },
            "lowerLimitLevel": 10,
            "upperLimitLevel": 44,
            "stageList": [
                24116,
                24117,
                24118,
                24119,
                24120
            ],
            "stageWeight": [
                1,
                2,
                4,
                8,
                16
            ],
            "mainId": [
                24116001,
                24117001,
                24118001,
                24119001,
                24120001
            ]
        },
        {
            "id": 100024,
            "typeId": 3,
            "groupId": 1,
            "typeName": {
                "id": "4435"
            },
            "lowerLimitLevel": 60,
            "stageList": [
                24141,
                24142,
                24143,
                24144,
                24145
            ],
            "stageWeight": [
                1,
                2,
                4,
                8,
                16
            ],
            "mainId": [
                24141001,
                24142001,
                24143001,
                24144001,
                24145001
            ]
        },
        {
            "id": 100025,
            "typeId": 3,
            "groupId": 2,
            "typeName": {
                "id": "4436"
            },
            "lowerLimitLevel": 45,
            "upperLimitLevel": 59,
            "stageList": [
                24136,
                24137,
                24138,
                24139,
                24140
            ],
            "stageWeight": [
                1,
                2,
                4,
                8,
                16
            ],
            "mainId": [
                24136001,
                24137001,
                24138001,
                24139001,
                24140001
            ]
        },
        {
            "id": 100026,
            "typeId": 3,
            "groupId": 3,
            "typeName": {
                "id": "4437"
            },
            "lowerLimitLevel": 10,
            "upperLimitLevel": 44,
            "stageList": [
                24131,
                24132,
                24133,
                24134,
                24135
            ],
            "stageWeight": [
                1,
                2,
                4,
                8,
                16
            ],
            "mainId": [
                24131001,
                24132001,
                24133001,
                24134001,
                24135001
            ]
        }
    ]
}