{
    "data": [
        {
            "id": 1,
            "xmin": 20,
            "ymin": 20,
            "xmax": 43,
            "ymax": 37,
            "gridNum": 149
        },
        {
            "id": 2,
            "xmin": 20,
            "ymin": 20,
            "xmax": 43,
            "ymax": 43,
            "gridNum": 92
        },
        {
            "id": 3,
            "xmin": 20,
            "ymin": 20,
            "xmax": 39,
            "ymax": 31,
            "gridNum": 148
        },
        {
            "id": 6,
            "xmin": 16,
            "ymin": 16,
            "xmax": 27,
            "ymax": 31,
            "gridNum": 128
        },
        {
            "id": 7,
            "xmin": 17,
            "ymin": 17,
            "xmax": 28,
            "ymax": 32,
            "gridNum": 106
        },
        {
            "id": 8,
            "xmin": 17,
            "ymin": 17,
            "xmax": 28,
            "ymax": 32,
            "gridNum": 103
        },
        {
            "id": 9,
            "xmin": 16,
            "ymin": 16,
            "xmax": 31,
            "ymax": 37,
            "gridNum": 205
        },
        {
            "id": 11,
            "xmin": 16,
            "ymin": 16,
            "xmax": 33,
            "ymax": 37,
            "gridNum": 222
        },
        {
            "id": 12,
            "xmin": 16,
            "ymin": 16,
            "xmax": 36,
            "ymax": 34,
            "gridNum": 121
        },
        {
            "id": 13,
            "xmin": 16,
            "ymin": 16,
            "xmax": 27,
            "ymax": 31,
            "gridNum": 134
        },
        {
            "id": 14,
            "xmin": 20,
            "ymin": 20,
            "xmax": 30,
            "ymax": 32,
            "gridNum": 81
        },
        {
            "id": 15,
            "xmin": 20,
            "ymin": 20,
            "xmax": 41,
            "ymax": 41,
            "gridNum": 125
        },
        {
            "id": 16,
            "xmin": 17,
            "ymin": 17,
            "xmax": 28,
            "ymax": 32,
            "gridNum": 80
        },
        {
            "id": 17,
            "xmin": 20,
            "ymin": 20,
            "xmax": 35,
            "ymax": 35,
            "gridNum": 101
        },
        {
            "id": 18,
            "xmin": 20,
            "ymin": 20,
            "xmax": 35,
            "ymax": 35,
            "gridNum": 72
        },
        {
            "id": 19,
            "xmin": 17,
            "ymin": 17,
            "xmax": 28,
            "ymax": 32,
            "gridNum": 80
        },
        {
            "id": 20,
            "xmin": 17,
            "ymin": 16,
            "xmax": 29,
            "ymax": 33,
            "gridNum": 87
        },
        {
            "id": 21,
            "xmin": 17,
            "ymin": 17,
            "xmax": 28,
            "ymax": 32,
            "gridNum": 87
        },
        {
            "id": 22,
            "xmin": 17,
            "ymin": 17,
            "xmax": 34,
            "ymax": 40,
            "gridNum": 152
        },
        {
            "id": 23,
            "xmin": 16,
            "ymin": 15,
            "xmax": 27,
            "ymax": 32,
            "gridNum": 73
        },
        {
            "id": 24,
            "xmin": 15,
            "ymin": 16,
            "xmax": 32,
            "ymax": 27,
            "gridNum": 77
        },
        {
            "id": 25,
            "xmin": 15,
            "ymin": 16,
            "xmax": 32,
            "ymax": 27,
            "gridNum": 84
        },
        {
            "id": 26,
            "xmin": 18,
            "ymin": 20,
            "xmax": 35,
            "ymax": 37,
            "gridNum": 78
        },
        {
            "id": 27,
            "xmin": 16,
            "ymin": 16,
            "xmax": 26,
            "ymax": 34,
            "gridNum": 132
        },
        {
            "id": 29,
            "xmin": 16,
            "ymin": 16,
            "xmax": 27,
            "ymax": 29,
            "gridNum": 70
        },
        {
            "id": 30,
            "xmin": 16,
            "ymin": 16,
            "xmax": 27,
            "ymax": 29,
            "gridNum": 75
        },
        {
            "id": 31,
            "xmin": 16,
            "ymin": 16,
            "xmax": 27,
            "ymax": 29,
            "gridNum": 74
        },
        {
            "id": 32,
            "xmin": 20,
            "ymin": 20,
            "xmax": 31,
            "ymax": 35,
            "gridNum": 82
        },
        {
            "id": 33,
            "xmin": 20,
            "ymin": 20,
            "xmax": 39,
            "ymax": 49,
            "gridNum": 292
        },
        {
            "id": 34,
            "xmin": 20,
            "ymin": 20,
            "xmax": 41,
            "ymax": 42,
            "gridNum": 199
        },
        {
            "id": 35,
            "xmin": 20,
            "ymin": 20,
            "xmax": 31,
            "ymax": 39,
            "gridNum": 68
        },
        {
            "id": 36,
            "xmin": 16,
            "ymin": 16,
            "xmax": 34,
            "ymax": 34,
            "gridNum": 99
        },
        {
            "id": 37,
            "xmin": 16,
            "ymin": 16,
            "xmax": 34,
            "ymax": 34,
            "gridNum": 109
        },
        {
            "id": 38,
            "xmin": 16,
            "ymin": 16,
            "xmax": 31,
            "ymax": 33,
            "gridNum": 124
        },
        {
            "id": 39,
            "xmin": 16,
            "ymin": 16,
            "xmax": 33,
            "ymax": 33,
            "gridNum": 156
        },
        {
            "id": 40,
            "xmin": 17,
            "ymin": 17,
            "xmax": 34,
            "ymax": 34,
            "gridNum": 130
        },
        {
            "id": 41,
            "xmin": 16,
            "ymin": 16,
            "xmax": 33,
            "ymax": 33,
            "gridNum": 189
        },
        {
            "id": 42,
            "xmin": 16,
            "ymin": 16,
            "xmax": 42,
            "ymax": 42,
            "gridNum": 208
        },
        {
            "id": 43,
            "xmin": 17,
            "ymin": 17,
            "xmax": 38,
            "ymax": 38,
            "gridNum": 164
        },
        {
            "id": 44,
            "xmin": 17,
            "ymin": 17,
            "xmax": 28,
            "ymax": 32,
            "gridNum": 90
        },
        {
            "id": 45,
            "xmin": 15,
            "ymin": 16,
            "xmax": 36,
            "ymax": 37,
            "gridNum": 142
        },
        {
            "id": 46,
            "xmin": 17,
            "ymin": 17,
            "xmax": 35,
            "ymax": 38,
            "gridNum": 154
        },
        {
            "id": 47,
            "xmin": 16,
            "ymin": 16,
            "xmax": 33,
            "ymax": 33,
            "gridNum": 146
        },
        {
            "id": 48,
            "xmin": 17,
            "ymin": 17,
            "xmax": 34,
            "ymax": 34,
            "gridNum": 178
        },
        {
            "id": 49,
            "xmin": 16,
            "ymin": 16,
            "xmax": 33,
            "ymax": 39,
            "gridNum": 156
        },
        {
            "id": 50,
            "xmin": 16,
            "ymin": 16,
            "xmax": 33,
            "ymax": 39,
            "gridNum": 106
        },
        {
            "id": 51,
            "xmin": 17,
            "ymin": 17,
            "xmax": 34,
            "ymax": 40,
            "gridNum": 126
        },
        {
            "id": 52,
            "xmin": 17,
            "ymin": 17,
            "xmax": 34,
            "ymax": 40,
            "gridNum": 128
        },
        {
            "id": 53,
            "xmin": 17,
            "ymin": 17,
            "xmax": 34,
            "ymax": 40,
            "gridNum": 128
        },
        {
            "id": 54,
            "xmin": 17,
            "ymin": 17,
            "xmax": 34,
            "ymax": 40,
            "gridNum": 122
        },
        {
            "id": 55,
            "xmin": 16,
            "ymin": 16,
            "xmax": 33,
            "ymax": 33,
            "gridNum": 154
        },
        {
            "id": 56,
            "xmin": 17,
            "ymin": 17,
            "xmax": 34,
            "ymax": 34,
            "gridNum": 102
        },
        {
            "id": 57,
            "xmin": 17,
            "ymin": 17,
            "xmax": 34,
            "ymax": 40,
            "gridNum": 205
        },
        {
            "id": 58,
            "xmin": 9,
            "ymin": 11,
            "xmax": 26,
            "ymax": 32,
            "gridNum": 80
        },
        {
            "id": 59,
            "xmin": 16,
            "ymin": 16,
            "xmax": 29,
            "ymax": 32,
            "gridNum": 110
        },
        {
            "id": 60,
            "xmin": 20,
            "ymin": 20,
            "xmax": 36,
            "ymax": 39,
            "gridNum": 72
        },
        {
            "id": 61,
            "xmin": 20,
            "ymin": 20,
            "xmax": 41,
            "ymax": 41,
            "gridNum": 67
        },
        {
            "id": 62,
            "xmin": 16,
            "ymin": 16,
            "xmax": 33,
            "ymax": 39,
            "gridNum": 153
        },
        {
            "id": 63,
            "xmin": 16,
            "ymin": 16,
            "xmax": 33,
            "ymax": 39,
            "gridNum": 178
        },
        {
            "id": 65,
            "xmin": 16,
            "ymin": 16,
            "xmax": 30,
            "ymax": 30,
            "gridNum": 9
        },
        {
            "id": 66,
            "xmin": 20,
            "ymin": 20,
            "xmax": 33,
            "ymax": 41,
            "gridNum": 111
        },
        {
            "id": 67,
            "xmin": 20,
            "ymin": 18,
            "xmax": 44,
            "ymax": 39,
            "gridNum": 167
        },
        {
            "id": 68,
            "xmin": 17,
            "ymin": 17,
            "xmax": 34,
            "ymax": 40,
            "gridNum": 152
        },
        {
            "id": 69,
            "xmin": 17,
            "ymin": 16,
            "xmax": 34,
            "ymax": 40,
            "gridNum": 142
        },
        {
            "id": 70,
            "xmin": 17,
            "ymin": 17,
            "xmax": 34,
            "ymax": 34,
            "gridNum": 102
        },
        {
            "id": 71,
            "xmin": 15,
            "ymin": 19,
            "xmax": 36,
            "ymax": 40,
            "gridNum": 176
        },
        {
            "id": 72,
            "xmin": 40,
            "ymin": 51,
            "xmax": 61,
            "ymax": 72,
            "gridNum": 247
        },
        {
            "id": 73,
            "xmin": 17,
            "ymin": 17,
            "xmax": 38,
            "ymax": 38,
            "gridNum": 44
        },
        {
            "id": 74,
            "xmin": 17,
            "ymin": 16,
            "xmax": 34,
            "ymax": 39,
            "gridNum": 209
        },
        {
            "id": 75,
            "xmin": 18,
            "ymin": 17,
            "xmax": 30,
            "ymax": 32,
            "gridNum": 130
        },
        {
            "id": 76,
            "xmin": 17,
            "ymin": 17,
            "xmax": 34,
            "ymax": 40,
            "gridNum": 161
        },
        {
            "id": 77,
            "xmin": 17,
            "ymin": 17,
            "xmax": 40,
            "ymax": 40,
            "gridNum": 136
        },
        {
            "id": 78,
            "xmin": 16,
            "ymin": 16,
            "xmax": 42,
            "ymax": 42,
            "gridNum": 226
        },
        {
            "id": 79,
            "xmin": 16,
            "ymin": 16,
            "xmax": 33,
            "ymax": 33,
            "gridNum": 174
        },
        {
            "id": 80,
            "xmin": 17,
            "ymin": 17,
            "xmax": 38,
            "ymax": 38,
            "gridNum": 165
        },
        {
            "id": 81,
            "xmin": 17,
            "ymin": 17,
            "xmax": 40,
            "ymax": 40,
            "gridNum": 160
        },
        {
            "id": 82,
            "xmin": 17,
            "ymin": 17,
            "xmax": 34,
            "ymax": 34,
            "gridNum": 178
        },
        {
            "id": 83,
            "xmin": 16,
            "ymin": 16,
            "xmax": 31,
            "ymax": 33,
            "gridNum": 116
        },
        {
            "id": 84,
            "xmin": 17,
            "ymin": 17,
            "xmax": 34,
            "ymax": 34,
            "gridNum": 111
        },
        {
            "id": 85,
            "xmin": 17,
            "ymin": 17,
            "xmax": 34,
            "ymax": 34,
            "gridNum": 130
        },
        {
            "id": 86,
            "xmin": 18,
            "ymin": 20,
            "xmax": 35,
            "ymax": 37,
            "gridNum": 185
        },
        {
            "id": 87,
            "xmin": 19,
            "ymin": 15,
            "xmax": 36,
            "ymax": 32,
            "gridNum": 248
        },
        {
            "id": 88,
            "xmin": 19,
            "ymin": 15,
            "xmax": 36,
            "ymax": 32,
            "gridNum": 273
        },
        {
            "id": 89,
            "xmin": 17,
            "ymin": 17,
            "xmax": 34,
            "ymax": 40,
            "gridNum": 115
        },
        {
            "id": 90,
            "xmin": 17,
            "ymin": 17,
            "xmax": 34,
            "ymax": 40,
            "gridNum": 143
        },
        {
            "id": 91,
            "xmin": 9,
            "ymin": 9,
            "xmax": 48,
            "ymax": 48,
            "gridNum": 156
        },
        {
            "id": 92,
            "xmin": 16,
            "ymin": 16,
            "xmax": 27,
            "ymax": 31,
            "gridNum": 102
        },
        {
            "id": 93,
            "xmin": 16,
            "ymin": 16,
            "xmax": 34,
            "ymax": 34,
            "gridNum": 131
        },
        {
            "id": 94,
            "xmin": 17,
            "ymin": 17,
            "xmax": 55,
            "ymax": 49,
            "gridNum": 728
        },
        {
            "id": 95,
            "xmin": 17,
            "ymin": 17,
            "xmax": 28,
            "ymax": 32,
            "gridNum": 89
        },
        {
            "id": 96,
            "xmin": 17,
            "ymin": 17,
            "xmax": 34,
            "ymax": 40,
            "gridNum": 119
        },
        {
            "id": 97,
            "xmin": 17,
            "ymin": 17,
            "xmax": 34,
            "ymax": 34,
            "gridNum": 164
        },
        {
            "id": 98,
            "xmin": 19,
            "ymin": 21,
            "xmax": 34,
            "ymax": 36,
            "gridNum": 49
        },
        {
            "id": 99,
            "xmin": 20,
            "ymin": 16,
            "xmax": 35,
            "ymax": 31,
            "gridNum": 102
        },
        {
            "id": 100,
            "xmin": 20,
            "ymin": 16,
            "xmax": 35,
            "ymax": 31,
            "gridNum": 119
        },
        {
            "id": 101,
            "xmin": 15,
            "ymin": 19,
            "xmax": 36,
            "ymax": 40,
            "gridNum": 151
        },
        {
            "id": 102,
            "xmin": 17,
            "ymin": 17,
            "xmax": 28,
            "ymax": 32,
            "gridNum": 72
        },
        {
            "id": 103,
            "xmin": 15,
            "ymin": 19,
            "xmax": 36,
            "ymax": 40,
            "gridNum": 110
        },
        {
            "id": 104,
            "xmin": 15,
            "ymin": 19,
            "xmax": 36,
            "ymax": 40,
            "gridNum": 110
        },
        {
            "id": 106,
            "xmin": 17,
            "ymin": 16,
            "xmax": 38,
            "ymax": 37,
            "gridNum": 162
        },
        {
            "id": 107,
            "xmin": 16,
            "ymin": 16,
            "xmax": 34,
            "ymax": 34,
            "gridNum": 146
        },
        {
            "id": 108,
            "xmin": 16,
            "ymin": 16,
            "xmax": 33,
            "ymax": 39,
            "gridNum": 167
        },
        {
            "id": 109,
            "xmin": 17,
            "ymin": 17,
            "xmax": 34,
            "ymax": 40,
            "gridNum": 171
        },
        {
            "id": 110,
            "xmin": 17,
            "ymin": 17,
            "xmax": 34,
            "ymax": 40,
            "gridNum": 110
        },
        {
            "id": 111,
            "xmin": 17,
            "ymin": 17,
            "xmax": 34,
            "ymax": 40,
            "gridNum": 148
        },
        {
            "id": 112,
            "xmin": 17,
            "ymin": 17,
            "xmax": 34,
            "ymax": 40,
            "gridNum": 169
        },
        {
            "id": 113,
            "xmin": 17,
            "ymin": 17,
            "xmax": 34,
            "ymax": 40,
            "gridNum": 171
        },
        {
            "id": 114,
            "xmin": 17,
            "ymin": 17,
            "xmax": 34,
            "ymax": 40,
            "gridNum": 170
        },
        {
            "id": 115,
            "xmin": 17,
            "ymin": 17,
            "xmax": 34,
            "ymax": 40,
            "gridNum": 164
        },
        {
            "id": 116,
            "xmin": 17,
            "ymin": 17,
            "xmax": 34,
            "ymax": 40,
            "gridNum": 165
        },
        {
            "id": 121,
            "xmin": 15,
            "ymin": 19,
            "xmax": 36,
            "ymax": 40,
            "gridNum": 144
        },
        {
            "id": 122,
            "xmin": 19,
            "ymin": 15,
            "xmax": 36,
            "ymax": 32,
            "gridNum": 244
        },
        {
            "id": 123,
            "xmin": 17,
            "ymin": 17,
            "xmax": 34,
            "ymax": 40,
            "gridNum": 194
        },
        {
            "id": 124,
            "xmin": 15,
            "ymin": 19,
            "xmax": 36,
            "ymax": 40,
            "gridNum": 150
        },
        {
            "id": 125,
            "xmin": 18,
            "ymin": 17,
            "xmax": 37,
            "ymax": 34,
            "gridNum": 116
        },
        {
            "id": 126,
            "xmin": 18,
            "ymin": 17,
            "xmax": 37,
            "ymax": 34,
            "gridNum": 116
        },
        {
            "id": 127,
            "xmin": 17,
            "ymin": 17,
            "xmax": 34,
            "ymax": 40,
            "gridNum": 121
        },
        {
            "id": 128,
            "xmin": 17,
            "ymin": 17,
            "xmax": 34,
            "ymax": 40,
            "gridNum": 117
        },
        {
            "id": 129,
            "xmin": 17,
            "ymin": 17,
            "xmax": 34,
            "ymax": 40,
            "gridNum": 116
        },
        {
            "id": 130,
            "xmin": 17,
            "ymin": 17,
            "xmax": 34,
            "ymax": 40,
            "gridNum": 148
        },
        {
            "id": 131,
            "xmin": 17,
            "ymin": 17,
            "xmax": 34,
            "ymax": 40,
            "gridNum": 117
        },
        {
            "id": 132,
            "xmin": 17,
            "ymin": 17,
            "xmax": 34,
            "ymax": 40,
            "gridNum": 125
        },
        {
            "id": 134,
            "xmin": 17,
            "ymin": 17,
            "xmax": 34,
            "ymax": 40,
            "gridNum": 122
        },
        {
            "id": 135,
            "xmin": 15,
            "ymin": 9,
            "xmax": 36,
            "ymax": 30,
            "gridNum": 170
        },
        {
            "id": 136,
            "xmin": 17,
            "ymin": 17,
            "xmax": 34,
            "ymax": 40,
            "gridNum": 126
        },
        {
            "id": 137,
            "xmin": 17,
            "ymin": 17,
            "xmax": 34,
            "ymax": 40,
            "gridNum": 130
        },
        {
            "id": 138,
            "xmin": 17,
            "ymin": 17,
            "xmax": 34,
            "ymax": 40,
            "gridNum": 60
        },
        {
            "id": 139,
            "xmin": 18,
            "ymin": 17,
            "xmax": 37,
            "ymax": 34,
            "gridNum": 116
        },
        {
            "id": 140,
            "xmin": 17,
            "ymin": 17,
            "xmax": 34,
            "ymax": 34,
            "gridNum": 143
        },
        {
            "id": 141,
            "xmin": 15,
            "ymin": 19,
            "xmax": 36,
            "ymax": 40,
            "gridNum": 158
        },
        {
            "id": 142,
            "xmin": 18,
            "ymin": 17,
            "xmax": 37,
            "ymax": 34,
            "gridNum": 116
        },
        {
            "id": 143,
            "xmin": 18,
            "ymin": 15,
            "xmax": 39,
            "ymax": 36,
            "gridNum": 130
        },
        {
            "id": 144,
            "xmin": 17,
            "ymin": 17,
            "xmax": 34,
            "ymax": 40,
            "gridNum": 194
        },
        {
            "id": 145,
            "xmin": 16,
            "ymin": 16,
            "xmax": 31,
            "ymax": 29,
            "gridNum": 142
        },
        {
            "id": 146,
            "xmin": 17,
            "ymin": 17,
            "xmax": 34,
            "ymax": 40,
            "gridNum": 125
        },
        {
            "id": 148,
            "xmin": 16,
            "ymin": 16,
            "xmax": 33,
            "ymax": 33,
            "gridNum": 122
        },
        {
            "id": 149,
            "xmin": 17,
            "ymin": 17,
            "xmax": 34,
            "ymax": 40,
            "gridNum": 171
        },
        {
            "id": 150,
            "xmin": 18,
            "ymin": 17,
            "xmax": 37,
            "ymax": 34,
            "gridNum": 146
        },
        {
            "id": 151,
            "xmin": 16,
            "ymin": 16,
            "xmax": 32,
            "ymax": 33,
            "gridNum": 185
        },
        {
            "id": 153,
            "xmin": 16,
            "ymin": 16,
            "xmax": 34,
            "ymax": 31,
            "gridNum": 198
        },
        {
            "id": 154,
            "xmin": 18,
            "ymin": 17,
            "xmax": 37,
            "ymax": 34,
            "gridNum": 111
        },
        {
            "id": 155,
            "xmin": 18,
            "ymin": 16,
            "xmax": 31,
            "ymax": 33,
            "gridNum": 145
        },
        {
            "id": 156,
            "xmin": 18,
            "ymin": 16,
            "xmax": 32,
            "ymax": 34,
            "gridNum": 159
        },
        {
            "id": 157,
            "xmin": 16,
            "ymin": 16,
            "xmax": 33,
            "ymax": 39,
            "gridNum": 154
        },
        {
            "id": 158,
            "xmin": 17,
            "ymin": 17,
            "xmax": 34,
            "ymax": 40,
            "gridNum": 149
        },
        {
            "id": 159,
            "xmin": 16,
            "ymin": 16,
            "xmax": 33,
            "ymax": 39,
            "gridNum": 143
        },
        {
            "id": 160,
            "xmin": 15,
            "ymin": 16,
            "xmax": 35,
            "ymax": 34,
            "gridNum": 76
        },
        {
            "id": 161,
            "xmin": 16,
            "ymin": 16,
            "xmax": 33,
            "ymax": 39,
            "gridNum": 155
        },
        {
            "id": 162,
            "xmin": 17,
            "ymin": 17,
            "xmax": 34,
            "ymax": 40,
            "gridNum": 195
        },
        {
            "id": 163,
            "xmin": 16,
            "ymin": 16,
            "xmax": 33,
            "ymax": 39,
            "gridNum": 151
        },
        {
            "id": 164,
            "xmin": 16,
            "ymin": 16,
            "xmax": 33,
            "ymax": 39,
            "gridNum": 150
        },
        {
            "id": 165,
            "xmin": 16,
            "ymin": 16,
            "xmax": 33,
            "ymax": 39,
            "gridNum": 191
        },
        {
            "id": 166,
            "xmin": 16,
            "ymin": 16,
            "xmax": 33,
            "ymax": 39,
            "gridNum": 133
        },
        {
            "id": 167,
            "xmin": 16,
            "ymin": 16,
            "xmax": 33,
            "ymax": 39,
            "gridNum": 148
        },
        {
            "id": 168,
            "xmin": 16,
            "ymin": 16,
            "xmax": 33,
            "ymax": 39,
            "gridNum": 162
        },
        {
            "id": 169,
            "xmin": 18,
            "ymin": 20,
            "xmax": 35,
            "ymax": 37,
            "gridNum": 91
        },
        {
            "id": 170,
            "xmin": 16,
            "ymin": 16,
            "xmax": 33,
            "ymax": 39,
            "gridNum": 180
        },
        {
            "id": 171,
            "xmin": 15,
            "ymin": 19,
            "xmax": 36,
            "ymax": 40,
            "gridNum": 62
        },
        {
            "id": 172,
            "xmin": 17,
            "ymin": 16,
            "xmax": 34,
            "ymax": 39,
            "gridNum": 206
        },
        {
            "id": 173,
            "xmin": 18,
            "ymin": 17,
            "xmax": 30,
            "ymax": 32,
            "gridNum": 130
        },
        {
            "id": 175,
            "xmin": 17,
            "ymin": 17,
            "xmax": 34,
            "ymax": 40,
            "gridNum": 154
        },
        {
            "id": 176,
            "xmin": 16,
            "ymin": 16,
            "xmax": 29,
            "ymax": 33,
            "gridNum": 152
        },
        {
            "id": 177,
            "xmin": 16,
            "ymin": 16,
            "xmax": 31,
            "ymax": 37,
            "gridNum": 216
        },
        {
            "id": 178,
            "xmin": 16,
            "ymin": 16,
            "xmax": 36,
            "ymax": 34,
            "gridNum": 122
        },
        {
            "id": 179,
            "xmin": 17,
            "ymin": 17,
            "xmax": 34,
            "ymax": 40,
            "gridNum": 207
        },
        {
            "id": 180,
            "xmin": 16,
            "ymin": 16,
            "xmax": 33,
            "ymax": 39,
            "gridNum": 142
        },
        {
            "id": 181,
            "xmin": 16,
            "ymin": 16,
            "xmax": 33,
            "ymax": 39,
            "gridNum": 152
        },
        {
            "id": 182,
            "xmin": 16,
            "ymin": 16,
            "xmax": 33,
            "ymax": 39,
            "gridNum": 191
        },
        {
            "id": 183,
            "xmin": 17,
            "ymin": 17,
            "xmax": 32,
            "ymax": 32,
            "gridNum": 143
        },
        {
            "id": 184,
            "xmin": 17,
            "ymin": 17,
            "xmax": 32,
            "ymax": 32,
            "gridNum": 147
        },
        {
            "id": 185,
            "xmin": 17,
            "ymin": 17,
            "xmax": 32,
            "ymax": 32,
            "gridNum": 143
        },
        {
            "id": 186,
            "xmin": 16,
            "ymin": 16,
            "xmax": 33,
            "ymax": 39,
            "gridNum": 144
        },
        {
            "id": 187,
            "xmin": 17,
            "ymin": 17,
            "xmax": 34,
            "ymax": 40,
            "gridNum": 168
        },
        {
            "id": 188,
            "xmin": 17,
            "ymin": 17,
            "xmax": 34,
            "ymax": 40,
            "gridNum": 171
        },
        {
            "id": 189,
            "xmin": 14,
            "ymin": 17,
            "xmax": 37,
            "ymax": 40,
            "gridNum": 184
        },
        {
            "id": 190,
            "xmin": 16,
            "ymin": 16,
            "xmax": 29,
            "ymax": 33,
            "gridNum": 152
        },
        {
            "id": 191,
            "xmin": 19,
            "ymin": 15,
            "xmax": 36,
            "ymax": 32,
            "gridNum": 117
        },
        {
            "id": 192,
            "xmin": 16,
            "ymin": 16,
            "xmax": 33,
            "ymax": 33,
            "gridNum": 70
        },
        {
            "id": 193,
            "xmin": 16,
            "ymin": 16,
            "xmax": 33,
            "ymax": 33,
            "gridNum": 203
        },
        {
            "id": 194,
            "xmin": 16,
            "ymin": 16,
            "xmax": 33,
            "ymax": 33,
            "gridNum": 160
        },
        {
            "id": 195,
            "xmin": 16,
            "ymin": 16,
            "xmax": 33,
            "ymax": 39,
            "gridNum": 137
        }
    ]
}